wallbreaker/__init__.py
wallbreaker/connection.py
wallbreaker/main.py
wallbreaker/utils.py
wallbreaker/agent/__init__.py
wallbreaker/agent/command/__init__.py
wallbreaker/agent/command/agent.js
wallbreaker-1.0.3.dist-info/METADATA
wallbreaker-1.0.3.dist-info/WHEEL
wallbreaker-1.0.3.dist-info/top_level.txt
wallbreaker-1.0.3.dist-info/RECORD
