Metadata-Version: 2.1
Name: wallbreaker
Version: 1.0.3
Summary: 🔨 Break Java Reverse Engineering form Memory World!
Home-page: https://github.com/hluwa/Wallbreaker
Author: hluwa
Author-email: hluwa888@gmail.com
License: UNKNOWN
Keywords: frida android wallbreaker objectdump objectsearch classdump classsearch
Platform: UNKNOWN
Classifier: Development Status :: 5 - Production/Stable
Classifier: License :: OSI Approved :: GNU General Public License v3 (GPLv3)
Classifier: Operating System :: MacOS :: MacOS X
Classifier: Operating System :: Microsoft :: Windows
Classifier: Operating System :: POSIX :: Linux
Classifier: Programming Language :: Python :: 3
Classifier: Programming Language :: Python :: 3.4
Classifier: Programming Language :: Python :: 3.5
Classifier: Programming Language :: Python :: 3.6
Classifier: Programming Language :: Python :: 3.7
Classifier: Programming Language :: Python :: 3.8
Requires-Dist: frida
Requires-Dist: click
